aws_sam_cli-1.151.0.dist-info/licenses/LICENSE
aws_sam_cli-1.151.0.dist-info/licenses/NOTICE
samcli/__init__.py
samcli/__main__.py
samcli/runtime_config.json
samcli/yamlhelper.py
samcli/cli/__init__.py
samcli/cli/cli_config_file.py
samcli/cli/command.py
samcli/cli/context.py
samcli/cli/formatters.py
samcli/cli/global_config.py
samcli/cli/hidden_imports.py
samcli/cli/import_module_proxy.py
samcli/cli/lazy_group.py
samcli/cli/main.py
samcli/cli/options.py
samcli/cli/row_modifiers.py
samcli/cli/types.py
samcli/cli/core/__init__.py
samcli/cli/core/command.py
samcli/cli/core/options.py
samcli/cli/root/__init__.py
samcli/cli/root/command_list.py
samcli/commands/__init__.py
samcli/commands/exceptions.py
samcli/commands/_utils/__init__.py
samcli/commands/_utils/cdk_support_decorators.py
samcli/commands/_utils/click_mutex.py
samcli/commands/_utils/command_exception_handler.py
samcli/commands/_utils/constants.py
samcli/commands/_utils/experimental.py
samcli/commands/_utils/option_validator.py
samcli/commands/_utils/option_value_processor.py
samcli/commands/_utils/options.py
samcli/commands/_utils/parameterized_option.py
samcli/commands/_utils/table_print.py
samcli/commands/_utils/template.py
samcli/commands/_utils/custom_options/__init__.py
samcli/commands/_utils/custom_options/hook_name_option.py
samcli/commands/_utils/custom_options/option_nargs.py
samcli/commands/_utils/custom_options/replace_help_option.py
samcli/commands/bootstrap/__init__.py
samcli/commands/bootstrap/command.py
samcli/commands/build/__init__.py
samcli/commands/build/build_context.py
samcli/commands/build/click_container.py
samcli/commands/build/command.py
samcli/commands/build/exceptions.py
samcli/commands/build/utils.py
samcli/commands/build/core/__init__.py
samcli/commands/build/core/command.py
samcli/commands/build/core/formatters.py
samcli/commands/build/core/options.py
samcli/commands/common/__init__.py
samcli/commands/common/formatters.py
samcli/commands/common/callback/fail/options.py
samcli/commands/common/callback/heartbeat/options.py
samcli/commands/common/callback/succeed/options.py
aws_sam_cli-1.151.0.dist-info/METADATA
aws_sam_cli-1.151.0.dist-info/WHEEL
aws_sam_cli-1.151.0.dist-info/entry_points.txt
aws_sam_cli-1.151.0.dist-info/top_level.txt
aws_sam_cli-1.151.0.dist-info/RECORD
