Metadata-Version: 2.4
Name: aws-sam-cli
Version: 1.151.0
Summary: AWS SAM CLI is a CLI tool for local development and testing of Serverless applications
Home-page: https://github.com/aws/aws-sam-cli
Author: Amazon Web Services
Author-email: aws-sam-developers@amazon.com
License: Apache License 2.0
Keywords: AWS SAM CLI
Classifier: Development Status :: 5 - Production/Stable
Classifier: Environment :: Console
Classifier: Environment :: Other Environment
Classifier: Intended Audience :: Developers
Classifier: Intended Audience :: Information Technology
Classifier: Operating System :: OS Independent
Classifier: Programming Language :: Python
Classifier: Programming Language :: Python :: 3.9
Classifier: Programming Language :: Python :: 3.11
Classifier: Topic :: Internet
Classifier: Topic :: Software Development :: Build Tools
Classifier: Topic :: Utilities
Requires-Python: >=3.9, <=4.0, !=4.0
License-File: LICENSE
License-File: NOTICE
Requires-Dist: chevron~=0.12
Requires-Dist: click==8.1.8
Requires-Dist: Flask<3.2
Requires-Dist: boto3[crt]==1.42.1
Requires-Dist: jmespath~=1.0.1
Requires-Dist: ruamel_yaml~=0.18.16
Requires-Dist: PyYAML~=6.0
Requires-Dist: cookiecutter~=2.6.0
Requires-Dist: aws-sam-translator==1.106.0
Requires-Dist: docker~=7.1.0
Requires-Dist: dateparser~=1.2
Requires-Dist: requests~=2.32.5
Requires-Dist: aws_lambda_builders==1.61.0
Requires-Dist: tomlkit==0.13.3
Requires-Dist: watchdog==4.0.2
Requires-Dist: rich~=14.2.0
Requires-Dist: pyopenssl~=25.3.0
Requires-Dist: jsonschema<4.26
Requires-Dist: typing_extensions<5,>=4.4.0
Requires-Dist: regex!=2021.10.8
Requires-Dist: tzlocal==5.3.1
Requires-Dist: cfn-lint~=1.43.0
Requires-Dist: boto3-stubs[apigateway,cloudformation,ecr,iam,kinesis,lambda,s3,schemas,secretsmanager,signer,sqs,stepfunctions,sts,xray]>=1.41.0
Provides-Extra: pre-dev
Requires-Dist: ruff==0.14.1; extra == "pre-dev"
Provides-Extra: dev
Requires-Dist: ruff==0.14.1; extra == "dev"
Requires-Dist: coverage==7.10.7; python_version >= "3.9" and extra == "dev"
Requires-Dist: coverage==7.6.1; python_version < "3.9" and extra == "dev"
Requires-Dist: pytest-cov==7.0.0; python_version >= "3.9" and extra == "dev"
Requires-Dist: pytest-cov==5.0.0; python_version < "3.9" and extra == "dev"
Requires-Dist: mypy==1.18.2; extra == "dev"
Requires-Dist: types-pywin32==311.0.0.20251008; python_version >= "3.9" and extra == "dev"
Requires-Dist: types-pywin32==308.0.0.20241221; python_version < "3.9" and extra == "dev"
Requires-Dist: types-PyYAML==6.0.12.20250915; extra == "dev"
Requires-Dist: types-chevron==0.14.2.20250103; extra == "dev"
Requires-Dist: types-psutil==7.1.3.20251202; extra == "dev"
Requires-Dist: types-setuptools==80.9.0.20250822; extra == "dev"
Requires-Dist: types-Pygments==2.19.0.20251121; extra == "dev"
Requires-Dist: types-colorama==0.4.15.20250801; extra == "dev"
Requires-Dist: types-dateparser==1.2.2.20250809; extra == "dev"
Requires-Dist: types-docutils==0.22.3.20251115; extra == "dev"
Requires-Dist: types-jsonschema==4.25.1.20251009; extra == "dev"
Requires-Dist: types-pyOpenSSL==24.1.0.20240722; extra == "dev"
Requires-Dist: types-requests==2.31.0.6; python_version < "3.10" and extra == "dev"
Requires-Dist: types-requests==2.32.4.20250913; python_version >= "3.10" and extra == "dev"
Requires-Dist: types-urllib3==1.26.25.14; extra == "dev"
Requires-Dist: pytest==8.4.1; extra == "dev"
Requires-Dist: parameterized==0.9.0; extra == "dev"
Requires-Dist: pytest-xdist==3.8.0; extra == "dev"
Requires-Dist: pytest-forked==1.6.0; extra == "dev"
Requires-Dist: pytest-timeout==2.4.0; extra == "dev"
Requires-Dist: pytest-rerunfailures==16.1; python_version >= "3.10" and extra == "dev"
Requires-Dist: pytest-rerunfailures==16.0.1; python_version < "3.10" and extra == "dev"
Requires-Dist: pytest-metadata==3.1.1; extra == "dev"
Requires-Dist: pytest-json-report-wip==1.5.1; extra == "dev"
Requires-Dist: filelock==3.20.0; python_version >= "3.10" and extra == "dev"
Requires-Dist: filelock==3.19.1; python_version < "3.10" and extra == "dev"
Requires-Dist: black==25.9.0; python_version >= "3.9" and extra == "dev"
Requires-Dist: black==24.8.0; python_version < "3.9" and extra == "dev"
Requires-Dist: psutil==7.1.1; extra == "dev"
Dynamic: author
Dynamic: author-email
Dynamic: classifier
Dynamic: description
Dynamic: description-content-type
Dynamic: home-page
Dynamic: keywords
Dynamic: license
Dynamic: license-file
Dynamic: provides-extra
Dynamic: requires-dist
Dynamic: requires-python
Dynamic: summary
